{"inkVersion":20,"root":[["^(This a nice home!)","\n","^(Within the city so they can see their grandkids WHENEVER)","\n","^(There does seem to be more of an older presence in this area)","\n","^(Which I am sure will lend a lot to their social life)","\n","^(They won't feel out of place here)","\n","^(There is a mall nearby as well which I am sure will come in handy)","\n","^(Shannon will be able to start a garden here as well)","\n","^(There is no farming however haha)","\n","^(Overall it is a solid property that is within the budget)","\n","^(Time to head back!)","\n",["done",{"#f":5,"#n":"g-0"}],null],"done",{"#f":1}],"listDefs":{}}